{"metadata": {"dbt_schema_version": "https://schemas.getdbt.com/dbt/run-results/v5.json", "dbt_version": "1.7.18", "generated_at": "2026-04-24T21:46:53.432999Z", "invocation_id": "8c7d8ee0-9e5f-40ef-8053-1d6b67230ea2", "env": {}}, "results": [{"status": "error", "timing": [{"name": "compile", "started_at": "2026-04-24T21:46:52.353796Z", "completed_at": "2026-04-24T21:46:52.360797Z"}, {"name": "execute", "started_at": "2026-04-24T21:46:52.394795Z", "completed_at": "2026-04-24T21:46:52.771153Z"}], "thread_id": "Thread-3", "execution_time": 0.5548441410064697, "adapter_response": {}, "message": "Database Error in model stg_orders (models\\staging\\stg_orders.sql)\n  002003 (02000): SQL compilation error:\n  Schema 'RAW_DATA.SHOPCO_PRODUCTION' does not exist or not authorized.\n  compiled Code at target\\run\\shopco_analytics\\models\\staging\\stg_orders.sql", "failures": null, "unique_id": "model.shopco_analytics.stg_orders", "compiled": true, "compiled_code": "\n\nWITH source AS (\n    SELECT * FROM raw_data.shopco_production.raw_orders\n),\n\ncleaned AS (\n    SELECT\n        order_id,\n        customer_id,\n        order_date,\n        DATE_TRUNC('month', order_date) AS order_month,\n        DATE_TRUNC('quarter', order_date) AS order_quarter,\n        DATE_TRUNC('year', order_date) AS order_year,\n        EXTRACT(YEAR FROM order_date) AS order_year_number,\n        EXTRACT(MONTH FROM order_date) AS order_month_number,\n        DATEDIFF('day', order_date, CURRENT_DATE) AS days_since_order,\n        LOWER(TRIM(order_status)) AS order_status,\n        total_amount,\n        LOWER(TRIM(payment_method)) AS payment_method,\n        CASE WHEN LOWER(order_status) = 'delivered' THEN TRUE ELSE FALSE END AS is_delivered,\n        CASE WHEN LOWER(order_status) = 'cancelled' THEN TRUE ELSE FALSE END AS is_cancelled,\n        CURRENT_TIMESTAMP AS dbt_loaded_at\n    FROM source\n    WHERE order_id IS NOT NULL\n      AND total_amount > 0\n)\n\nSELECT * FROM cleaned", "relation_name": "ANALYTICS.DEV_xdai_staging.stg_orders"}, {"status": "error", "timing": [{"name": "compile", "started_at": "2026-04-24T21:46:52.350796Z", "completed_at": "2026-04-24T21:46:52.358795Z"}, {"name": "execute", "started_at": "2026-04-24T21:46:52.361797Z", "completed_at": "2026-04-24T21:46:52.795409Z"}], "thread_id": "Thread-4", "execution_time": 0.5678441524505615, "adapter_response": {}, "message": "Database Error in model stg_products (models\\staging\\stg_products.sql)\n  002003 (02000): SQL compilation error:\n  Schema 'RAW_DATA.SHOPCO_PRODUCTION' does not exist or not authorized.\n  compiled Code at target\\run\\shopco_analytics\\models\\staging\\stg_products.sql", "failures": null, "unique_id": "model.shopco_analytics.stg_products", "compiled": true, "compiled_code": "\n\nWITH source AS (\n    SELECT * FROM raw_data.shopco_production.raw_products\n),\n\ncleaned AS (\n    SELECT\n        product_id,\n        TRIM(product_name) AS product_name,\n        LOWER(TRIM(category)) AS category,\n        LOWER(TRIM(subcategory)) AS subcategory,\n        TRIM(brand) AS brand,\n        current_price,\n        cost,\n        current_price - cost AS margin,\n        ROUND((current_price - cost) / NULLIF(current_price, 0) * 100, 2) AS margin_percent,\n        CASE\n            WHEN current_price < 20 THEN 'budget'\n            WHEN current_price BETWEEN 20 AND 100 THEN 'mid_range'\n            WHEN current_price BETWEEN 101 AND 500 THEN 'premium'\n            ELSE 'luxury'\n        END AS price_tier,\n        CURRENT_TIMESTAMP AS dbt_loaded_at\n    FROM source\n    WHERE product_id IS NOT NULL\n      AND current_price > 0\n)\n\nSELECT * FROM cleaned", "relation_name": "ANALYTICS.DEV_xdai_staging.stg_products"}, {"status": "error", "timing": [{"name": "compile", "started_at": "2026-04-24T21:46:52.338795Z", "completed_at": "2026-04-24T21:46:52.358795Z"}, {"name": "execute", "started_at": "2026-04-24T21:46:52.387795Z", "completed_at": "2026-04-24T21:46:52.784870Z"}], "thread_id": "Thread-1", "execution_time": 0.6258442401885986, "adapter_response": {}, "message": "Database Error in model stg_customers (models\\staging\\stg_customers.sql)\n  002003 (02000): SQL compilation error:\n  Schema 'RAW_DATA.SHOPCO_PRODUCTION' does not exist or not authorized.\n  compiled Code at target\\run\\shopco_analytics\\models\\staging\\stg_customers.sql", "failures": null, "unique_id": "model.shopco_analytics.stg_customers", "compiled": true, "compiled_code": "\n\nWITH source AS (\n    SELECT * FROM raw_data.shopco_production.raw_customers\n),\n\ncleaned AS (\n    SELECT\n        customer_id,\n        LOWER(TRIM(email)) AS email,\n        INITCAP(TRIM(first_name)) AS first_name,\n        INITCAP(TRIM(last_name)) AS last_name,\n        INITCAP(TRIM(first_name)) || ' ' || INITCAP(TRIM(last_name)) AS full_name,\n        created_at,\n        UPPER(TRIM(country)) AS country,\n        LOWER(TRIM(customer_tier)) AS customer_tier,\n        CURRENT_TIMESTAMP AS dbt_loaded_at\n    FROM source\n    WHERE customer_id IS NOT NULL\n)\n\nSELECT * FROM cleaned", "relation_name": "ANALYTICS.DEV_xdai_staging.stg_customers"}, {"status": "error", "timing": [{"name": "compile", "started_at": "2026-04-24T21:46:52.346795Z", "completed_at": "2026-04-24T21:46:52.360797Z"}, {"name": "execute", "started_at": "2026-04-24T21:46:52.391795Z", "completed_at": "2026-04-24T21:46:52.802577Z"}], "thread_id": "Thread-2", "execution_time": 0.6248447895050049, "adapter_response": {}, "message": "Database Error in model stg_order_items (models\\staging\\stg_order_items.sql)\n  002003 (02000): SQL compilation error:\n  Schema 'RAW_DATA.SHOPCO_PRODUCTION' does not exist or not authorized.\n  compiled Code at target\\run\\shopco_analytics\\models\\staging\\stg_order_items.sql", "failures": null, "unique_id": "model.shopco_analytics.stg_order_items", "compiled": true, "compiled_code": "\n\nWITH source AS (\n    SELECT * FROM raw_data.shopco_production.raw_order_items\n),\n\ncleaned AS (\n    SELECT\n        order_item_id,\n        order_id,\n        product_id,\n        quantity,\n        CASE\n            WHEN quantity = 1 THEN 'single'\n            WHEN quantity BETWEEN 2 AND 5 THEN 'small_batch'\n            WHEN quantity BETWEEN 6 AND 20 THEN 'medium_batch'\n            ELSE 'bulk'\n        END AS quantity_tier,\n        unit_price,\n        quantity * unit_price AS line_total,\n        CURRENT_TIMESTAMP AS dbt_loaded_at\n    FROM source\n    WHERE order_item_id IS NOT NULL\n      AND quantity > 0\n      AND unit_price > 0\n)\n\nSELECT * FROM cleaned", "relation_name": "ANALYTICS.DEV_xdai_staging.stg_order_items"}, {"status": "error", "timing": [{"name": "compile", "started_at": "2026-04-24T21:46:52.895639Z", "completed_at": "2026-04-24T21:46:52.904641Z"}, {"name": "execute", "started_at": "2026-04-24T21:46:52.905638Z", "completed_at": "2026-04-24T21:46:53.327701Z"}], "thread_id": "Thread-3", "execution_time": 0.5323588848114014, "adapter_response": {}, "message": "Database Error in model stg_web_events (models\\staging\\stg_web_events.sql)\n  002003 (02000): SQL compilation error:\n  Schema 'RAW_DATA.SHOPCO_PRODUCTION' does not exist or not authorized.\n  compiled Code at target\\run\\shopco_analytics\\models\\staging\\stg_web_events.sql", "failures": null, "unique_id": "model.shopco_analytics.stg_web_events", "compiled": true, "compiled_code": "\n\nWITH source AS (\n    SELECT * FROM raw_data.shopco_production.raw_web_events\n    \n),\n\ncleaned AS (\n    SELECT\n        event_id, session_id, customer_id,\n        LOWER(TRIM(event_type)) AS event_type,\n        event_timestamp,\n        DATE_TRUNC('hour', event_timestamp) AS event_hour,\n        DATE_TRUNC('day', event_timestamp) AS event_date,\n        page_url,\n        SPLIT_PART(page_url, '/', 3) AS page_domain,\n        SPLIT_PART(page_url, '/', 4) AS page_section,\n        product_id,\n        CASE WHEN LOWER(event_type) = 'page_view' THEN 1 ELSE 0 END AS is_page_view,\n        CASE WHEN LOWER(event_type) = 'product_view' THEN 1 ELSE 0 END AS is_product_view,\n        CASE WHEN LOWER(event_type) = 'add_to_cart' THEN 1 ELSE 0 END AS is_add_to_cart,\n        CASE WHEN LOWER(event_type) = 'checkout_start' THEN 1 ELSE 0 END AS is_checkout_start,\n        CASE WHEN customer_id IS NULL OR TRIM(customer_id) = '' THEN 'anonymous' ELSE 'logged_in' END AS user_type,\n        CURRENT_TIMESTAMP AS dbt_loaded_at\n    FROM source\n    WHERE event_id IS NOT NULL AND event_timestamp IS NOT NULL\n)\n\nSELECT * FROM cleaned", "relation_name": "ANALYTICS.DEV_xdai_staging.stg_web_events"}], "elapsed_time": 5.843414545059204, "args": {"log_level": "info", "strict_mode": false, "use_colors": true, "indirect_selection": "eager", "partial_parse": true, "cache_selected_only": false, "introspect": true, "invocation_command": "dbt run -s staging", "macro_debugging": false, "vars": {}, "select": ["staging"], "exclude": [], "enable_legacy_logger": false, "favor_state": false, "use_colors_file": true, "defer": false, "populate_cache": true, "printer_width": 80, "project_dir": "C:\\Users\\Xuan\\shopco_analytics", "which": "run", "log_level_file": "debug", "quiet": false, "log_format": "default", "partial_parse_file_diff": true, "static_parser": true, "warn_error_options": {"include": [], "exclude": []}, "log_format_file": "debug", "require_explicit_package_overrides_for_builtin_materializations": false, "print": true, "log_path": "C:\\Users\\Xuan\\shopco_analytics\\logs", "profiles_dir": "C:\\Users\\Xuan\\.dbt", "send_anonymous_usage_stats": true, "write_json": true, "show_resource_report": false, "version_check": true, "log_file_max_bytes": 10485760}}